jissues
