Metadata-Version: 2.1
Name: django-jissues
Version: 1.0.3
Summary: Basic issue tracking abstract data models for Django projects.
Home-page: https://github.com/kajala/django-jissues
Author: Jani Kajala
Author-email: kajala@gmail.com
License: MIT licence, see LICENCE.txt
License-File: LICENSE.txt
Requires-Dist: Django>=4.0
Requires-Dist: django-jutil>=4.1.1
